[
  {"name":"Tyrese Maxey","points":26.03,"line":29.5,"difference":-3.47},
  {"name":"VJ Edgecombe","points":16.15,"line":15.5,"difference":0.65},
  {"name":"Jay Huff","points":11.38,"line":11.5,"difference":-0.12},
  {"name":"Ben Sheppard","points":9.12,"line":7.5,"difference":1.62},
  {"name":"Nickeil Alexander-Walker","points":18.18,"line":18.5,"difference":-0.32},
  {"name":"Will Riley","points":12.17,"line":9.5,"difference":2.67},
  {"name":"Jock Landale","points":9.39,"line":8.5,"difference":0.89},
  {"name":"Naji Marshall","points":17.59,"line":17.5,"difference":0.09},
  {"name":"P.J. Washington","points":15.23,"line":16.5,"difference":-1.27},
  {"name":"Max Christie","points":14.47,"line":14.5,"difference":-0.03},
  {"name":"Nolan Traore","points":13.02,"line":11.5,"difference":1.52},
  {"name":"Egor Demin","points":11.74,"line":10.5,"difference":1.24},
  {"name":"Day'Ron Sharpe","points":10.06,"line":9.5,"difference":0.56},
  {"name":"Daniel Gafford","points":7.68,"line":8.5,"difference":-0.82},
  {"name":"Danny Wolf","points":11.31,"line":8.5,"difference":2.81},
  {"name":"Brandon Ingram","points":22.48,"line":19.5,"difference":2.98},
  {"name":"Scottie Barnes","points":16.76,"line":17.5,"difference":-0.74},
  {"name":"Immanuel Quickley","points":18.36,"line":15.5,"difference":2.86},
  {"name":"Isaiah Joe","points":14.24,"line":14.5,"difference":-0.26},
  {"name":"Cason Wallace","points":13.8,"line":10.5,"difference":3.3},
  {"name":"Sandro Mamukelashvili","points":11.01,"line":10.5,"difference":0.51},
  {"name":"Jared McCain","points":9.58,"line":10.5,"difference":-0.92},
  {"name":"Collin Murray-Boyles","points":7.87,"line":8.5,"difference":-0.63},
  {"name":"Jamal Shead","points":7.17,"line":5.5,"difference":1.67},
  {"name":"Brandon Miller","points":21.64,"line":21.5,"difference":0.14},
  {"name":"LaMelo Ball","points":23.04,"line":19.5,"difference":3.54},
  {"name":"Kon Knueppel","points":20.48,"line":17.5,"difference":2.98},
  {"name":"Matas Buzelis","points":14.63,"line":15.5,"difference":-0.87},
  {"name":"Isaac Okoro","points":12.79,"line":10.5,"difference":2.29},
  {"name":"Patrick Williams","points":9.94,"line":8.5,"difference":1.44},
  {"name":"Ryan Kalkbrenner","points":7.93,"line":5.5,"difference":2.43},
  {"name":"Kevin Porter Jr.","points":17.95,"line":17.5,"difference":0.45},
  {"name":"Ryan Rollins","points":21.74,"line":17.5,"difference":4.24},
  {"name":"Bam Adebayo","points":19.8,"line":17.5,"difference":2.3},
  {"name":"Cam Thomas","points":14.94,"line":14.5,"difference":0.44},
  {"name":"Kyle Kuzma","points":12.97,"line":11.5,"difference":1.47},
  {"name":"Bobby Portis","points":13.27,"line":10.5,"difference":2.77},
  {"name":"Kel'el Ware","points":12.4,"line":8.5,"difference":3.9},
  {"name":"Payton Pritchard","points":21.56,"line":21.5,"difference":0.06},
  {"name":"Jalen Green","points":16.05,"line":20.5,"difference":-4.45},
  {"name":"Derrick White","points":16.88,"line":19.5,"difference":-2.62},
  {"name":"Grayson Allen","points":20.27,"line":17.5,"difference":2.77},
  {"name":"Collin Gillespie","points":13.76,"line":16.5,"difference":-2.74},
  {"name":"Nikola Vucevic","points":13.85,"line":13.5,"difference":0.35},
  {"name":"Mark Williams","points":10.17,"line":10.5,"difference":-0.33},
  {"name":"Neemias Queta","points":8.05,"line":10.5,"difference":-2.45},
  {"name":"Royce O'Neale","points":10.48,"line":9.5,"difference":0.98},
  {"name":"Baylor Scheierman","points":8.04,"line":9.5,"difference":-1.46},
  {"name":"Ryan Dunn","points":6.63,"line":6.5,"difference":0.13},
  {"name":"Oso Ighodaro","points":7.24,"line":5.5,"difference":1.74},
  {"name":"Anthony Edwards","points":25.63,"line":28.5,"difference":-2.87},
  {"name":"Julius Randle","points":19.95,"line":20.5,"difference":-0.55},
  {"name":"Jaden McDaniels","points":14.85,"line":14.5,"difference":0.35},
  {"name":"Ayo Dosunmu","points":14.17,"line":12.5,"difference":1.67},
  {"name":"Donte DiVincenzo","points":9.49,"line":10.5,"difference":-1.01},
  {"name":"Luka Doncic","points":28.34,"line":31.5,"difference":-3.16},
  {"name":"Paolo Banchero","points":21.17,"line":21.5,"difference":-0.33},
  {"name":"Desmond Bane","points":20.6,"line":20.5,"difference":0.1},
  {"name":"LeBron James","points":21.16,"line":18.5,"difference":2.66},
  {"name":"Anthony Black","points":15.68,"line":15.5,"difference":0.18},
  {"name":"Jalen Suggs","points":12.1,"line":13.5,"difference":-1.4},
  {"name":"Rui Hachimura","points":10.24,"line":8.5,"difference":1.74},
  {"name":"Tristan da Silva","points":8.7,"line":7.5,"difference":1.2},
  {"name":"Marcus Smart","points":9.22,"line":6.5,"difference":2.72}
]